sdx/common/__init__.py
sdx/common/log_levels.py
sdx/common/logger_config.py
sdx_common-1.0.2.dist-info/DESCRIPTION.rst
sdx_common-1.0.2.dist-info/METADATA
sdx_common-1.0.2.dist-info/RECORD
sdx_common-1.0.2.dist-info/WHEEL
sdx_common-1.0.2.dist-info/entry_points.txt
sdx_common-1.0.2.dist-info/metadata.json
sdx_common-1.0.2.dist-info/top_level.txt
