Metadata-Version: 2.0
Name: sdx-common
Version: 1.0.2
Summary: A shared library for SDX services
Home-page: https://github.com/ONSdigital/sdx-common
Author: D Haynes
Author-email: tundish@thuswise.org
License: UNKNOWN
Platform: UNKNOWN
Classifier: Operating System :: OS Independent
Classifier: Programming Language :: Python :: 3.4
Classifier: Programming Language :: Python :: 3.5
Classifier: License :: OSI Approved :: Apache Software License
Provides-Extra: dev
Requires-Dist: flake8 (>=2.6.0); extra == 'dev'
Requires-Dist: pep8 (>=1.6.2); extra == 'dev'
Provides-Extra: docbuild
Requires-Dist: sphinx-argparse (>=0.1.17); extra == 'docbuild'
Requires-Dist: sphinx-rtd-theme (>=0.2.4); extra == 'docbuild'
Requires-Dist: sphinxcontrib-seqdiag (>=0.8.5); extra == 'docbuild'
